{
  "games": [
    {
      "id": "Qu__",
      "title": "Qu__",
      "image": "game-thumbnails/Qu__.png",
      "detailFile": "game-details/qu.json"
    },
    {
      "id": "◼",
      "title": "◼",
      "image": "game-thumbnails/square.png",
      "detailFile": "game-details/square.json"
    },
    {
      "id": "Yesterday",
      "title": "Yesterday",
      "image": "game-thumbnails/yesterday.png",
      "detailFile": "game-details/yesterday.json"
    },
    {
      "id": "JDD",
      "title": "J-D-D",
      "image": "game-thumbnails/jdd.png",
      "detailFile": "game-details/jdd.json"
    },
    {
      "id": "howtoproperlyfallasleep",
      "title": "how to properly fall asleep",
      "image": "game-thumbnails/howtoproperlyfallasleep.png",
      "detailFile": "game-details/howtoproperlyfallasleep.json"
    }
  ]
}
